[{"사업자번호":"2561202171","년월":"202402","브랜드":"떡참","행사":"FR첫주문할인","쿠폰":"3500","분담금":"2100.0","건수":22,"총합계":46200.0,"과금1차":23100.0,"과금2차":23100.0},{"사업자번호":"2561202171","년월":"202402","브랜드":"떡참","행사":"기획전(통합_1주)","쿠폰":"2000","분담금":"1200.0","건수":77,"총합계":92400.0,"과금1차":46200.0,"과금2차":46200.0},{"사업자번호":"2561202171","년월":"202402","브랜드":"떡참","행사":"기획전(통합_1주)","쿠폰":"3000","분담금":"1800.0","건수":32,"총합계":57600.0,"과금1차":28800.0,"과금2차":28800.0},{"사업자번호":"2561202171","년월":"202402","브랜드":"떡참","행사":"기획전(통합_1주)","쿠폰":"4000","분담금":"2400.0","건수":2,"총합계":4800.0,"과금1차":2400.0,"과금2차":2400.0},{"사업자번호":"2561202171","년월":"202402","브랜드":"떡참","행사":"기획전(통합_3주)","쿠폰":"2000","분담금":"1200.0","건수":65,"총합계":78000.0,"과금1차":39000.0,"과금2차":39000.0},{"사업자번호":"2561202171","년월":"202402","브랜드":"떡참","행사":"기획전(통합_3주)","쿠폰":"3000","분담금":"1800.0","건수":47,"총합계":84600.0,"과금1차":42300.0,"과금2차":42300.0},{"사업자번호":"2561202171","년월":"202402","브랜드":"떡참","행사":"브랜드관","쿠폰":"2000","분담금":"1200.0","건수":117,"총합계":140400.0,"과금1차":70200.0,"과금2차":70200.0},{"사업자번호":"2561202171","년월":"202402","브랜드":"떡참","행사":"브랜드관","쿠폰":"3000","분담금":"1800.0","건수":88,"총합계":158400.0,"과금1차":79200.0,"과금2차":79200.0},{"사업자번호":"2561202171","년월":"202402","브랜드":"떡참","행사":"브랜드찜","쿠폰":"3000","분담금":"1800.0","건수":1,"총합계":1800.0,"과금1차":900.0,"과금2차":900.0},{"사업자번호":"2561202171","년월":"202401","브랜드":"떡참","행사":"FR첫주문할인","쿠폰":"3000","분담금":"1800.0","건수":76,"총합계":136800.0,"과금1차":68400.0,"과금2차":68400.0},{"사업자번호":"2561202171","년월":"202401","브랜드":"떡참","행사":"기획전(통합_2주)","쿠폰":"2000","분담금":"1200.0","건수":92,"총합계":110400.0,"과금1차":55200.0,"과금2차":55200.0},{"사업자번호":"2561202171","년월":"202401","브랜드":"떡참","행사":"기획전(통합_2주)","쿠폰":"3000","분담금":"1800.0","건수":65,"총합계":117000.0,"과금1차":58500.0,"과금2차":58500.0},{"사업자번호":"2561202171","년월":"202401","브랜드":"떡참","행사":"브랜드찜","쿠폰":"2000","분담금":"1200.0","건수":2,"총합계":2400.0,"과금1차":1200.0,"과금2차":1200.0},{"사업자번호":"2561202171","년월":"202401","브랜드":"떡참","행사":"브랜드찜","쿠폰":"3000","분담금":"1800.0","건수":2,"총합계":3600.0,"과금1차":1800.0,"과금2차":1800.0}]