[{"사업자번호":"2670301748","년월":"202401","브랜드":"두찜","행사":"기획전(키워드쿠폰)","쿠폰":"3000","분담금":"1800.0","건수":18,"총합계":32400.0,"과금1차[1\/24(수)~26(금)]":16200.0,"과금2차[2\/7(수)~9(금)]":16200.0},{"사업자번호":"2670301748","년월":"202401","브랜드":"두찜","행사":"기획전(통합_2주)","쿠폰":"3000","분담금":"1800.0","건수":513,"총합계":923400.0,"과금1차[1\/24(수)~26(금)]":461700.0,"과금2차[2\/7(수)~9(금)]":461700.0},{"사업자번호":"2670301748","년월":"202401","브랜드":"두찜","행사":"배민선물하기","쿠폰":"-","분담금":"60%","건수":9,"총합계":27810.0,"과금1차[1\/24(수)~26(금)]":27810.0,"과금2차[2\/7(수)~9(금)]":0.0},{"사업자번호":"2670301748","년월":"202401","브랜드":"두찜","행사":"브랜드찜","쿠폰":"3000","분담금":"1800.0","건수":18,"총합계":32400.0,"과금1차[1\/24(수)~26(금)]":16200.0,"과금2차[2\/7(수)~9(금)]":16200.0}]