[{"사업자번호":"3580801641","년월":"202401","브랜드":"두찜","행사":"기획전(키워드쿠폰)","쿠폰":"3000","분담금":"1800.0","건수":2,"총합계":3600.0,"과금1차[02\/21(수)~23(금)]":1800.0,"과금2차[03\/06(수)~08(금)]":1800.0},{"사업자번호":"3580801641","년월":"202401","브랜드":"두찜","행사":"기획전(통합_2주)","쿠폰":"3000","분담금":"1800.0","건수":92,"총합계":165600.0,"과금1차[02\/21(수)~23(금)]":82800.0,"과금2차[03\/06(수)~08(금)]":82800.0},{"사업자번호":"3580801641","년월":"202401","브랜드":"두찜","행사":"브랜드찜","쿠폰":"3000","분담금":"1800.0","건수":2,"총합계":3600.0,"과금1차[02\/21(수)~23(금)]":1800.0,"과금2차[03\/06(수)~08(금)]":1800.0}]