[{"사업자번호":"6862000632","년월":"202402","브랜드":"두찜","행사":"FR첫주문할인","쿠폰":"4000","분담금":"2400.0","건수":176,"총합계":422400.0,"과금1차":211200.0,"과금2차":211200.0},{"사업자번호":"6862000632","년월":"202402","브랜드":"두찜","행사":"기획전(통합_3주)","쿠폰":"3000","분담금":"1800.0","건수":119,"총합계":214200.0,"과금1차":107100.0,"과금2차":107100.0},{"사업자번호":"6862000632","년월":"202402","브랜드":"두찜","행사":"단독배너(배달홈 유동형)","쿠폰":"3000","분담금":"1800.0","건수":157,"총합계":282600.0,"과금1차":141300.0,"과금2차":141300.0},{"사업자번호":"6862000632","년월":"202402","브랜드":"두찜","행사":"배민선물하기","쿠폰":"-","분담금":"60%","건수":1,"총합계":1854.0,"과금1차":1854.0,"과금2차":0.0},{"사업자번호":"6862000632","년월":"202402","브랜드":"두찜","행사":"브랜드관","쿠폰":"3000","분담금":"1800.0","건수":353,"총합계":635400.0,"과금1차":317700.0,"과금2차":317700.0},{"사업자번호":"6862000632","년월":"202402","브랜드":"두찜","행사":"브랜드찜","쿠폰":"3000","분담금":"1800.0","건수":5,"총합계":9000.0,"과금1차":4500.0,"과금2차":4500.0},{"사업자번호":"6862000632","년월":"202401","브랜드":"두찜","행사":"기획전(키워드쿠폰)","쿠폰":"3000","분담금":"1800.0","건수":13,"총합계":23400.0,"과금1차":11700.0,"과금2차":11700.0},{"사업자번호":"6862000632","년월":"202401","브랜드":"두찜","행사":"기획전(통합_2주)","쿠폰":"3000","분담금":"1800.0","건수":280,"총합계":504000.0,"과금1차":252000.0,"과금2차":252000.0},{"사업자번호":"6862000632","년월":"202401","브랜드":"두찜","행사":"배민선물하기","쿠폰":"-","분담금":"60%","건수":2,"총합계":5562.0,"과금1차":5562.0,"과금2차":0.0},{"사업자번호":"6862000632","년월":"202401","브랜드":"두찜","행사":"브랜드찜","쿠폰":"3000","분담금":"1800.0","건수":17,"총합계":30600.0,"과금1차":15300.0,"과금2차":15300.0}]