[{"사업자번호":"8440301754","년월":"202402","브랜드":"두찜","행사":"FR첫주문할인","쿠폰":"4000","분담금":"2400.0","건수":126,"총합계":302400.0,"과금1차":151200.0,"과금2차":151200.0},{"사업자번호":"8440301754","년월":"202402","브랜드":"두찜","행사":"기획전(통합_3주)","쿠폰":"3000","분담금":"1800.0","건수":73,"총합계":131400.0,"과금1차":65700.0,"과금2차":65700.0},{"사업자번호":"8440301754","년월":"202402","브랜드":"두찜","행사":"단독배너(배달홈 유동형)","쿠폰":"3000","분담금":"1800.0","건수":132,"총합계":237600.0,"과금1차":118800.0,"과금2차":118800.0},{"사업자번호":"8440301754","년월":"202402","브랜드":"두찜","행사":"배민선물하기","쿠폰":"-","분담금":"60%","건수":1,"총합계":1854.0,"과금1차":1854.0,"과금2차":0.0},{"사업자번호":"8440301754","년월":"202402","브랜드":"두찜","행사":"브랜드관","쿠폰":"3000","분담금":"1800.0","건수":262,"총합계":471600.0,"과금1차":235800.0,"과금2차":235800.0},{"사업자번호":"8440301754","년월":"202402","브랜드":"두찜","행사":"브랜드찜","쿠폰":"3000","분담금":"1800.0","건수":4,"총합계":7200.0,"과금1차":3600.0,"과금2차":3600.0},{"사업자번호":"8440301754","년월":"202401","브랜드":"두찜","행사":"기획전(키워드쿠폰)","쿠폰":"3000","분담금":"1800.0","건수":13,"총합계":23400.0,"과금1차":11700.0,"과금2차":11700.0},{"사업자번호":"8440301754","년월":"202401","브랜드":"두찜","행사":"기획전(통합_2주)","쿠폰":"3000","분담금":"1800.0","건수":242,"총합계":435600.0,"과금1차":217800.0,"과금2차":217800.0},{"사업자번호":"8440301754","년월":"202401","브랜드":"두찜","행사":"배민선물하기","쿠폰":"-","분담금":"60%","건수":1,"총합계":1854.0,"과금1차":1854.0,"과금2차":0.0},{"사업자번호":"8440301754","년월":"202401","브랜드":"두찜","행사":"브랜드찜","쿠폰":"3000","분담금":"1800.0","건수":24,"총합계":43200.0,"과금1차":21600.0,"과금2차":21600.0}]