[{"사업자번호":"8934601054","년월":"202404","브랜드":"숯불","행사":"FR첫주문할인","쿠폰":"4000","분담금":"2400.0","건수":130,"총합계":312000.0,"과금1차":156000.0,"과금2차":156000.0},{"사업자번호":"8934601054","년월":"202404","브랜드":"숯불","행사":"기획전(키워드쿠폰)","쿠폰":"3000","분담금":"1800.0","건수":1,"총합계":1800.0,"과금1차":900.0,"과금2차":900.0},{"사업자번호":"8934601054","년월":"202404","브랜드":"숯불","행사":"단독배너(배달홈 유동형)","쿠폰":"3000","분담금":"1800.0","건수":27,"총합계":48600.0,"과금1차":24300.0,"과금2차":24300.0},{"사업자번호":"8934601054","년월":"202404","브랜드":"숯불","행사":"메뉴할인","쿠폰":"1100","분담금":"660.0","건수":10,"총합계":6600.0,"과금1차":3300.0,"과금2차":3300.0},{"사업자번호":"8934601054","년월":"202404","브랜드":"숯불","행사":"메뉴할인","쿠폰":"1200","분담금":"720.0","건수":20,"총합계":14400.0,"과금1차":7200.0,"과금2차":7200.0},{"사업자번호":"8934601054","년월":"202404","브랜드":"숯불","행사":"메뉴할인","쿠폰":"1400","분담금":"840.0","건수":3,"총합계":2520.0,"과금1차":1260.0,"과금2차":1260.0},{"사업자번호":"8934601054","년월":"202404","브랜드":"숯불","행사":"브랜드찜","쿠폰":"3000","분담금":"1800.0","건수":35,"총합계":63000.0,"과금1차":31500.0,"과금2차":31500.0}]