[{"사업자번호":"1114900726","년월":"202402","브랜드":"두찜","행사":"FR첫주문할인","쿠폰":"4000","분담금":"2400.0","건수":91,"총합계":218400.0,"과금1차":109200.0,"과금2차":109200.0},{"사업자번호":"1114900726","년월":"202402","브랜드":"두찜","행사":"기획전(통합_3주)","쿠폰":"3000","분담금":"1800.0","건수":37,"총합계":66600.0,"과금1차":33300.0,"과금2차":33300.0},{"사업자번호":"1114900726","년월":"202402","브랜드":"두찜","행사":"단독배너(배달홈 유동형)","쿠폰":"3000","분담금":"1800.0","건수":68,"총합계":122400.0,"과금1차":61200.0,"과금2차":61200.0},{"사업자번호":"1114900726","년월":"202402","브랜드":"두찜","행사":"브랜드관","쿠폰":"3000","분담금":"1800.0","건수":175,"총합계":315000.0,"과금1차":157500.0,"과금2차":157500.0},{"사업자번호":"1114900726","년월":"202402","브랜드":"두찜","행사":"브랜드찜","쿠폰":"3000","분담금":"1800.0","건수":4,"총합계":7200.0,"과금1차":3600.0,"과금2차":3600.0},{"사업자번호":"1114900726","년월":"202401","브랜드":"두찜","행사":"기획전(키워드쿠폰)","쿠폰":"3000","분담금":"1800.0","건수":3,"총합계":5400.0,"과금1차":2700.0,"과금2차":2700.0},{"사업자번호":"1114900726","년월":"202401","브랜드":"두찜","행사":"기획전(통합_2주)","쿠폰":"3000","분담금":"1800.0","건수":164,"총합계":295200.0,"과금1차":147600.0,"과금2차":147600.0},{"사업자번호":"1114900726","년월":"202401","브랜드":"두찜","행사":"브랜드찜","쿠폰":"3000","분담금":"1800.0","건수":6,"총합계":10800.0,"과금1차":5400.0,"과금2차":5400.0}]